esinet/__init__.py
esinet/custom_layers.py
esinet/losses.py
esinet/net.py
esinet/simulation.py
esinet/evaluate/__init__.py
esinet/evaluate/evaluate.py
esinet/forward/__init__.py
esinet/forward/forward.py
esinet/minimum_norm/__init__.py
esinet/minimum_norm/minimum_norm.py
esinet/tests/__init__.py
esinet/tests/test_net.py
esinet/tests/test_simulation.py
esinet/util/__init__.py
esinet/util/util.py
esinet/viz/__init__.py
esinet/viz/cmaps.py
esinet/viz/viz.py
esinet-0.3.0.dist-info/LICENSE
esinet-0.3.0.dist-info/METADATA
esinet-0.3.0.dist-info/WHEEL
esinet-0.3.0.dist-info/top_level.txt
esinet-0.3.0.dist-info/RECORD
