Metadata-Version: 2.1
Name: esinet
Version: 0.3.0
Summary: Solves the M/EEG inverse problem using artificial neural networks with Python 3 and the MNE library.
Home-page: https://github.com/LukeTheHecker/esinet
Author: Lukas Hecker
Author-email: lukas_hecker@web.de
Classifier: Programming Language :: Python :: 3
Classifier: License :: OSI Approved :: MIT License
Classifier: Operating System :: OS Independent
Requires-Python: >=3.6
License-File: LICENSE
Requires-Dist: tensorflow
Requires-Dist: mne >=1.7.0
Requires-Dist: scipy
Requires-Dist: colorednoise
Requires-Dist: joblib
Requires-Dist: matplotlib
Requires-Dist: pyvista
Requires-Dist: pyvistaqt
Requires-Dist: vtk
Requires-Dist: tqdm
Requires-Dist: pytest
Requires-Dist: dill
Requires-Dist: scikit-learn
Requires-Dist: pandas
